AssCheck/__init__.py
AssCheck/bcolors.py
AssCheck/funcchecks.py
AssCheck/function_error_messages.py
AssCheck/plot_error_messages.py
AssCheck/plotchecks.py
AssCheck/plotclass.py
AssCheck/plotting_error_messages.py
AssCheck/test.py
AssCheck/varchecks.py
AssCheck/variable_error_messages.py
AssCheck-0.1.5.dist-info/METADATA
AssCheck-0.1.5.dist-info/WHEEL
AssCheck-0.1.5.dist-info/top_level.txt
AssCheck-0.1.5.dist-info/RECORD
