Metadata-Version: 2.1
Name: AssCheck
Version: 0.1.5
Summary: check basic python exercises with pretty feedback
Home-page: https://github.com/QUBAMA1021/test_utils
Author: Andrew Brown
Author-email: andrew.brown@qub.ac.uk
License: MIT
Platform: UNKNOWN
